complete_json/__init__.py
complete_json/_complete.py
complete_json-0.0.1.dist-info/LICENSE
complete_json-0.0.1.dist-info/METADATA
complete_json-0.0.1.dist-info/WHEEL
complete_json-0.0.1.dist-info/RECORD
